rocheml/__init__.py
rocheml/callbacks/__init__.py
rocheml/callbacks/trainingmonitor.py
rocheml/cv/__init__.py
rocheml/cv/face/__init__.py
rocheml/cv/face/facedetector.py
rocheml/cv/face/faceextractor.py
rocheml/cv/face/faceposeextractor.py
rocheml/cv/face/fastmtcnn.py
rocheml/datasetio/__init__.py
rocheml/datasetio/datasetgenerator.py
rocheml/datasetio/datasetgenerator2.py
rocheml/datasetio/datasetwriter.py
rocheml/datasetio/sequenceaugmentor.py
rocheml/preprocessing/__init__.py
rocheml/preprocessing/contrastpreprocessor.py
rocheml/preprocessing/croppreprocessor.py
rocheml/preprocessing/imagetoarraypreprocessor.py
rocheml/preprocessing/inceptionv3preprocessor.py
rocheml/preprocessing/meanpreprocessor.py
rocheml/preprocessing/rescalepreprocessor.py
rocheml/preprocessing/resizepreprocessor.py
rocheml/preprocessing/standardizepreprocessor.py
rocheml/test/__init__.py
rocheml/test/context.py
rocheml/test/test_datasetgenerator.py
rocheml/test/test_datasetwriter.py
rocheml-1.3.dist-info/LICENSE
rocheml-1.3.dist-info/METADATA
rocheml-1.3.dist-info/WHEEL
rocheml-1.3.dist-info/top_level.txt
rocheml-1.3.dist-info/RECORD
