Metadata-Version: 2.1
Name: rocheml
Version: 1.3
Summary: A package of useful machine learning classes and functions.
Home-page: UNKNOWN
Author: Hayden Roche
Author-email: haydenroche5@gmail.com
License: UNKNOWN
Platform: UNKNOWN
Classifier: Programming Language :: Python :: 3
Classifier: License :: OSI Approved :: MIT License
Classifier: Operating System :: OS Independent
Requires-Python: >=3.5
